llm_sampler/__init__.py
llm_sampler/closed_sampling.py
llm_sampler/gpt_fast.py
llm_sampler/hf.py
llm_sampler/utils.py
llm_sampler-0.4.0.dist-info/METADATA
llm_sampler-0.4.0.dist-info/WHEEL
llm_sampler-0.4.0.dist-info/top_level.txt
llm_sampler-0.4.0.dist-info/RECORD
